lastversion/__about__.py
lastversion/__init__.py
lastversion/__main__.py
lastversion/ai.py
lastversion/argparse_version.py
lastversion/cache.py
lastversion/cli.py
lastversion/config.py
lastversion/exceptions.py
lastversion/holder_factory.py
lastversion/lastversion.py
lastversion/spdx_id_to_rpmspec.py
lastversion/utils.py
lastversion/version.py
lastversion/repo_holders/__init__.py
lastversion/repo_holders/alpine.py
lastversion/repo_holders/base.py
lastversion/repo_holders/bibucket.py
lastversion/repo_holders/feed.py
lastversion/repo_holders/gitea.py
lastversion/repo_holders/github.py
lastversion/repo_holders/gitlab.py
lastversion/repo_holders/helmchat.py
lastversion/repo_holders/local.py
lastversion/repo_holders/mercurial.py
lastversion/repo_holders/pypi.py
lastversion/repo_holders/sourceforge.py
lastversion/repo_holders/system.py
lastversion/repo_holders/test.py
lastversion/repo_holders/wikipedia.py
lastversion/repo_holders/wordpress.py
lastversion-3.6.7.dist-info/licenses/LICENSE
lastversion-3.6.7.dist-info/METADATA
lastversion-3.6.7.dist-info/WHEEL
lastversion-3.6.7.dist-info/entry_points.txt
lastversion-3.6.7.dist-info/top_level.txt
lastversion-3.6.7.dist-info/RECORD
