Metadata-Version: 2.4
Name: lastversion
Version: 3.6.7
Summary: A CLI tool to find the latest stable version of an arbitrary project
Home-page: https://github.com/dvershinin/lastversion
Author: Danila Vershinin
Author-email: info@getpagespeed.com
License: BSD
Keywords: version,release,latest,stable,pypi,github,gitlab,bitbucket,mercurial,hg,wordpress
Classifier: Intended Audience :: Developers
Classifier: Intended Audience :: System Administrators
Classifier: Operating System :: OS Independent
Classifier: Topic :: Software Development
Classifier: Topic :: Software Development :: Libraries :: Python Modules
Classifier: Topic :: Software Development :: Version Control
Classifier: Topic :: Utilities
Classifier: License :: OSI Approved :: BSD License
Classifier: Environment :: Console
Classifier: Development Status :: 5 - Production/Stable
Classifier: Programming Language :: Python :: 3.6
Classifier: Programming Language :: Python :: 3.7
Classifier: Programming Language :: Python :: 3.8
Classifier: Programming Language :: Python :: 3.9
Classifier: Programming Language :: Python :: 3.10
Classifier: Programming Language :: Python :: 3.11
Classifier: Programming Language :: Python :: 3.12
Requires-Python: >=3.6
License-File: LICENSE
Requires-Dist: requests>=2.16.0
Requires-Dist: packaging
Requires-Dist: cachecontrol[filecache]<0.14,>=0.12.6; python_version < "3.10"
Requires-Dist: cachecontrol[filecache]>=0.14.0; python_version >= "3.10"
Requires-Dist: urllib3<2; python_version < "3.9"
Requires-Dist: appdirs
Requires-Dist: feedparser
Requires-Dist: python-dateutil
Requires-Dist: PyYAML
Requires-Dist: tqdm
Requires-Dist: beautifulsoup4
Requires-Dist: distro
Provides-Extra: tests
Requires-Dist: requests>=2.16.0; extra == "tests"
Requires-Dist: packaging; extra == "tests"
Requires-Dist: cachecontrol[filecache]<0.14,>=0.12.6; python_version < "3.10" and extra == "tests"
Requires-Dist: cachecontrol[filecache]>=0.14.0; python_version >= "3.10" and extra == "tests"
Requires-Dist: urllib3<2; python_version < "3.9" and extra == "tests"
Requires-Dist: appdirs; extra == "tests"
Requires-Dist: feedparser; extra == "tests"
Requires-Dist: python-dateutil; extra == "tests"
Requires-Dist: PyYAML; extra == "tests"
Requires-Dist: tqdm; extra == "tests"
Requires-Dist: beautifulsoup4; extra == "tests"
Requires-Dist: distro; extra == "tests"
Requires-Dist: pytest>=4.4.0; extra == "tests"
Requires-Dist: flake8; extra == "tests"
Requires-Dist: flake8-bugbear; extra == "tests"
Requires-Dist: pytest-xdist; extra == "tests"
Requires-Dist: pytest-cov; extra == "tests"
Provides-Extra: docs
Requires-Dist: mkdocs==1.5.3; extra == "docs"
Requires-Dist: mkdocs-material==9.5.3; extra == "docs"
Requires-Dist: mkdocstrings[python]; extra == "docs"
Requires-Dist: markdown-include; extra == "docs"
Provides-Extra: build
Requires-Dist: requests>=2.16.0; extra == "build"
Requires-Dist: packaging; extra == "build"
Requires-Dist: cachecontrol[filecache]<0.14,>=0.12.6; python_version < "3.10" and extra == "build"
Requires-Dist: cachecontrol[filecache]>=0.14.0; python_version >= "3.10" and extra == "build"
Requires-Dist: urllib3<2; python_version < "3.9" and extra == "build"
Requires-Dist: appdirs; extra == "build"
Requires-Dist: feedparser; extra == "build"
Requires-Dist: python-dateutil; extra == "build"
Requires-Dist: PyYAML; extra == "build"
Requires-Dist: tqdm; extra == "build"
Requires-Dist: beautifulsoup4; extra == "build"
Requires-Dist: distro; extra == "build"
Requires-Dist: pytest>=4.4.0; extra == "build"
Requires-Dist: flake8; extra == "build"
Requires-Dist: flake8-bugbear; extra == "build"
Requires-Dist: pytest-xdist; extra == "build"
Requires-Dist: pytest-cov; extra == "build"
Requires-Dist: mkdocs==1.5.3; extra == "build"
Requires-Dist: mkdocs-material==9.5.3; extra == "build"
Requires-Dist: mkdocstrings[python]; extra == "build"
Requires-Dist: markdown-include; extra == "build"
Provides-Extra: 7z
Requires-Dist: py7zr; extra == "7z"
Provides-Extra: truststore
Requires-Dist: truststore; extra == "truststore"
Provides-Extra: redis
Requires-Dist: redis>=3.0.0; extra == "redis"
Dynamic: author
Dynamic: author-email
Dynamic: classifier
Dynamic: description
Dynamic: description-content-type
Dynamic: home-page
Dynamic: keywords
Dynamic: license
Dynamic: license-file
Dynamic: provides-extra
Dynamic: requires-dist
Dynamic: requires-python
Dynamic: summary
